[{"code": "036010", "KS&KQ": "KQ"}, {"code": "001680", "KS&KQ": "KS"}, {"code": "131970", "KS&KQ": "KQ"}, {"code": "006110", "KS&KQ": "KS"}, {"code": "007540", "KS&KQ": "KS"}, {"code": "083640", "KS&KQ": "KQ"}, {"code": "217270", "KS&KQ": "KQ"}, {"code": "000950", "KS&KQ": "KS"}, {"code": "035900", "KS&KQ": "KQ"}, {"code": "090370", "KS&KQ": "KS"}, {"code": "047400", "KS&KQ": "KS"}, {"code": "071950", "KS&KQ": "KS"}, {"code": "095340", "KS&KQ": "KQ"}, {"code": "282690", "KS&KQ": "KS"}, {"code": "161000", "KS&KQ": "KS"}, {"code": "204620", "KS&KQ": "KQ"}, {"code": "034940", "KS&KQ": "KQ"}, {"code": "187220", "KS&KQ": "KQ"}, {"code": "105550", "KS&KQ": "KQ"}, {"code": "033790", "KS&KQ": "KQ"}, {"code": "089230", "KS&KQ": "KQ"}, {"code": "000400", "KS&KQ": "KS"}, {"code": "004100", "KS&KQ": "KS"}, {"code": "011280", "KS&KQ": "KS"}, {"code": "038160", "KS&KQ": "KQ"}, {"code": "258610", "KS&KQ": "KQ"}, {"code": "001520", "KS&KQ": "KS"}, {"code": "024950", "KS&KQ": "KQ"}, {"code": "900040", "KS&KQ": "KQ"}, {"code": "121800", "KS&KQ": "KQ"}, {"code": "009140", "KS&KQ": "KS"}, {"code": "008470", "KS&KQ": "KQ"}, {"code": "153460", "KS&KQ": "KQ"}, {"code": "040420", "KS&KQ": "KQ"}, {"code": "196700", "KS&KQ": "KQ"}, {"code": "078140", "KS&KQ": "KQ"}, {"code": "023150", "KS&KQ": "KS"}, {"code": "013520", "KS&KQ": "KS"}, {"code": "048530", "KS&KQ": "KQ"}, {"code": "053110", "KS&KQ": "KQ"}, {"code": "044450", "KS&KQ": "KS"}, {"code": "290120", "KS&KQ": "KQ"}, {"code": "238090", "KS&KQ": "KQ"}, {"code": "290650", "KS&KQ": "KQ"}, {"code": "023350", "KS&KQ": "KS"}, {"code": "004710", "KS&KQ": "KS"}, {"code": "033180", "KS&KQ": "KS"}, {"code": "130660", "KS&KQ": "KS"}, {"code": "094840", "KS&KQ": "KQ"}, {"code": "241790", "KS&KQ": "KQ"}, {"code": "040350", "KS&KQ": "KQ"}, {"code": "016670", "KS&KQ": "KQ"}, {"code": "029480", "KS&KQ": "KQ"}, {"code": "105630", "KS&KQ": "KS"}, {"code": "187790", "KS&KQ": "KQ"}, {"code": "089030", "KS&KQ": "KQ"}, {"code": "053270", "KS&KQ": "KQ"}, {"code": "001250", "KS&KQ": "KS"}, {"code": "008260", "KS&KQ": "KS"}, {"code": "039240", "KS&KQ": "KQ"}, {"code": "214430", "KS&KQ": "KQ"}, {"code": "227950", "KS&KQ": "KQ"}, {"code": "001720", "KS&KQ": "KS"}, {"code": "066590", "KS&KQ": "KQ"}, {"code": "009180", "KS&KQ": "KS"}, {"code": "276920", "KS&KQ": "KQ"}, {"code": "064350", "KS&KQ": "KS"}, {"code": "248170", "KS&KQ": "KS"}, {"code": "052190", "KS&KQ": "KQ"}, {"code": "085810", "KS&KQ": "KQ"}, {"code": "011320", "KS&KQ": "KQ"}, {"code": "086060", "KS&KQ": "KQ"}, {"code": "060240", "KS&KQ": "KQ"}, {"code": "252500", "KS&KQ": "KQ"}, {"code": "284620", "KS&KQ": "KQ"}, {"code": "205470", "KS&KQ": "KQ"}, {"code": "208140", "KS&KQ": "KQ"}, {"code": "058730", "KS&KQ": "KS"}, {"code": "110990", "KS&KQ": "KQ"}, {"code": "003720", "KS&KQ": "KS"}, {"code": "083450", "KS&KQ": "KQ"}, {"code": "018670", "KS&KQ": "KS"}, {"code": "221840", "KS&KQ": "KQ"}, {"code": "009190", "KS&KQ": "KS"}, {"code": "091120", "KS&KQ": "KQ"}, {"code": "222420", "KS&KQ": "KQ"}, {"code": "023590", "KS&KQ": "KS"}, {"code": "098460", "KS&KQ": "KQ"}, {"code": "058650", "KS&KQ": "KS"}, {"code": "002210", "KS&KQ": "KS"}, {"code": "093520", "KS&KQ": "KQ"}, {"code": "153710", "KS&KQ": "KQ"}, {"code": "101730", "KS&KQ": "KQ"}, {"code": "079660", "KS&KQ": "KS"}, {"code": "019180", "KS&KQ": "KS"}, {"code": "053260", "KS&KQ": "KQ"}, {"code": "093050", "KS&KQ": "KS"}, {"code": "126600", "KS&KQ": "KQ"}, {"code": "004270", "KS&KQ": "KS"}, {"code": "089140", "KS&KQ": "KQ"}, {"code": "053300", "KS&KQ": "KQ"}, {"code": "307070", "KS&KQ": "KQ"}, {"code": "035720", "KS&KQ": "KS"}, {"code": "004700", "KS&KQ": "KS"}, {"code": "291210", "KS&KQ": "KQ"}, {"code": "035250", "KS&KQ": "KS"}, {"code": "007590", "KS&KQ": "KS"}, {"code": "003090", "KS&KQ": "KS"}, {"code": "115180", "KS&KQ": "KQ"}, {"code": "126560", "KS&KQ": "KS"}, {"code": "041510", "KS&KQ": "KQ"}, {"code": "001120", "KS&KQ": "KS"}, {"code": "009540", "KS&KQ": "KS"}, {"code": "183490", "KS&KQ": "KQ"}, {"code": "039130", "KS&KQ": "KS"}, {"code": "013120", "KS&KQ": "KQ"}, {"code": "293940", "KS&KQ": "KS"}, {"code": "001530", "KS&KQ": "KS"}, {"code": "024940", "KS&KQ": "KQ"}, {"code": "104460", "KS&KQ": "KQ"}, {"code": "027050", "KS&KQ": "KQ"}, {"code": "003680", "KS&KQ": "KS"}, {"code": "006920", "KS&KQ": "KQ"}, {"code": "022100", "KS&KQ": "KQ"}, {"code": "001040", "KS&KQ": "KS"}, {"code": "033780", "KS&KQ": "KS"}, {"code": "182360", "KS&KQ": "KQ"}, {"code": "010170", "KS&KQ": "KQ"}, {"code": "066970", "KS&KQ": "KQ"}, {"code": "226320", "KS&KQ": "KS"}, {"code": "008930", "KS&KQ": "KS"}, {"code": "017810", "KS&KQ": "KS"}, {"code": "149950", "KS&KQ": "KQ"}, {"code": "014100", "KS&KQ": "KQ"}, {"code": "046120", "KS&KQ": "KQ"}, {"code": "178780", "KS&KQ": "KQ"}, {"code": "098660", "KS&KQ": "KQ"}, {"code": "048870", "KS&KQ": "KQ"}, {"code": "257730", "KS&KQ": "KQ"}, {"code": "281410", "KS&KQ": "KQ"}, {"code": "029530", "KS&KQ": "KS"}, {"code": "017390", "KS&KQ": "KS"}, {"code": "065060", "KS&KQ": "KQ"}, {"code": "054450", "KS&KQ": "KQ"}, {"code": "090360", "KS&KQ": "KQ"}, {"code": "003520", "KS&KQ": "KS"}, {"code": "051500", "KS&KQ": "KQ"}, {"code": "036570", "KS&KQ": "KS"}, {"code": "009780", "KS&KQ": "KQ"}, {"code": "064550", "KS&KQ": "KQ"}, {"code": "300720", "KS&KQ": "KS"}, {"code": "025530", "KS&KQ": "KS"}, {"code": "223310", "KS&KQ": "KQ"}, {"code": "083650", "KS&KQ": "KQ"}, {"code": "018470", "KS&KQ": "KS"}, {"code": "170900", "KS&KQ": "KS"}, {"code": "069510", "KS&KQ": "KQ"}, {"code": "120110", "KS&KQ": "KS"}, {"code": "220180", "KS&KQ": "KQ"}, {"code": "005390", "KS&KQ": "KS"}, {"code": "049830", "KS&KQ": "KQ"}, {"code": "039340", "KS&KQ": "KQ"}, {"code": "090850", "KS&KQ": "KQ"}, {"code": "064090", "KS&KQ": "KQ"}, {"code": "044340", "KS&KQ": "KQ"}, {"code": "016360", "KS&KQ": "KS"}, {"code": "009240", "KS&KQ": "KS"}, {"code": "005320", "KS&KQ": "KS"}, {"code": "078650", "KS&KQ": "KQ"}, {"code": "115480", "KS&KQ": "KQ"}, {"code": "104200", "KS&KQ": "KQ"}, {"code": "016610", "KS&KQ": "KS"}, {"code": "094940", "KS&KQ": "KQ"}, {"code": "045300", "KS&KQ": "KQ"}, {"code": "097520", "KS&KQ": "KQ"}, {"code": "152330", "KS&KQ": "KS"}, {"code": "009320", "KS&KQ": "KS"}, {"code": "084010", "KS&KQ": "KS"}, {"code": "043200", "KS&KQ": "KQ"}, {"code": "007330", "KS&KQ": "KQ"}, {"code": "051360", "KS&KQ": "KQ"}, {"code": "128660", "KS&KQ": "KQ"}, {"code": "047310", "KS&KQ": "KQ"}, {"code": "043610", "KS&KQ": "KQ"}, {"code": "003220", "KS&KQ": "KS"}, {"code": "002880", "KS&KQ": "KS"}, {"code": "006370", "KS&KQ": "KS"}, {"code": "249420", "KS&KQ": "KS"}, {"code": "168330", "KS&KQ": "KQ"}, {"code": "253450", "KS&KQ": "KQ"}, {"code": "263020", "KS&KQ": "KQ"}, {"code": "001810", "KS&KQ": "KQ"}, {"code": "005860", "KS&KQ": "KQ"}, {"code": "024110", "KS&KQ": "KS"}, {"code": "005690", "KS&KQ": "KS"}, {"code": "078860", "KS&KQ": "KQ"}, {"code": "099320", "KS&KQ": "KQ"}, {"code": "115440", "KS&KQ": "KQ"}, {"code": "290380", "KS&KQ": "KQ"}, {"code": "036460", "KS&KQ": "KS"}, {"code": "041830", "KS&KQ": "KQ"}, {"code": "013810", "KS&KQ": "KQ"}, {"code": "000850", "KS&KQ": "KS"}, {"code": "072020", "KS&KQ": "KQ"}, {"code": "040910", "KS&KQ": "KQ"}, {"code": "065560", "KS&KQ": "KQ"}, {"code": "226350", "KS&KQ": "KQ"}, {"code": "048430", "KS&KQ": "KQ"}, {"code": "177830", "KS&KQ": "KQ"}, {"code": "046390", "KS&KQ": "KQ"}, {"code": "079160", "KS&KQ": "KS"}, {"code": "019680", "KS&KQ": "KS"}, {"code": "134060", "KS&KQ": "KQ"}, {"code": "181340", "KS&KQ": "KQ"}, {"code": "032820", "KS&KQ": "KQ"}, {"code": "004410", "KS&KQ": "KS"}, {"code": "150900", "KS&KQ": "KQ"}, {"code": "039020", "KS&KQ": "KQ"}, {"code": "013030", "KS&KQ": "KQ"}, {"code": "900140", "KS&KQ": "KS"}, {"code": "084370", "KS&KQ": "KQ"}, {"code": "246710", "KS&KQ": "KQ"}, {"code": "259630", "KS&KQ": "KQ"}, {"code": "067000", "KS&KQ": "KQ"}, {"code": "298050", "KS&KQ": "KS"}, {"code": "036930", "KS&KQ": "KQ"}, {"code": "045060", "KS&KQ": "KQ"}, {"code": "017040", "KS&KQ": "KS"}, {"code": "206650", "KS&KQ": "KQ"}, {"code": "023440", "KS&KQ": "KQ"}, {"code": "170030", "KS&KQ": "KQ"}, {"code": "054800", "KS&KQ": "KQ"}, {"code": "215600", "KS&KQ": "KQ"}, {"code": "287410", "KS&KQ": "KQ"}, {"code": "015860", "KS&KQ": "KS"}, {"code": "053160", "KS&KQ": "KQ"}, {"code": "001140", "KS&KQ": "KS"}, {"code": "078130", "KS&KQ": "KQ"}, {"code": "221980", "KS&KQ": "KQ"}, {"code": "024840", "KS&KQ": "KQ"}, {"code": "067170", "KS&KQ": "KQ"}, {"code": "011780", "KS&KQ": "KS"}, {"code": "007690", "KS&KQ": "KS"}, {"code": "038460", "KS&KQ": "KQ"}, {"code": "047920", "KS&KQ": "KQ"}, {"code": "001020", "KS&KQ": "KS"}, {"code": "057500", "KS&KQ": "KQ"}, {"code": "090710", "KS&KQ": "KQ"}, {"code": "267320", "KS&KQ": "KQ"}, {"code": "066910", "KS&KQ": "KQ"}, {"code": "069410", "KS&KQ": "KQ"}, {"code": "001790", "KS&KQ": "KS"}, {"code": "271740", "KS&KQ": "KQ"}, {"code": "298690", "KS&KQ": "KS"}, {"code": "058430", "KS&KQ": "KS"}, {"code": "060150", "KS&KQ": "KQ"}, {"code": "277480", "KS&KQ": "KQ"}, {"code": "020560", "KS&KQ": "KS"}, {"code": "100840", "KS&KQ": "KS"}, {"code": "042520", "KS&KQ": "KQ"}, {"code": "071840", "KS&KQ": "KS"}, {"code": "027390", "KS&KQ": "KS"}, {"code": "003540", "KS&KQ": "KS"}, {"code": "005870", "KS&KQ": "KS"}, {"code": "025550", "KS&KQ": "KQ"}, {"code": "081580", "KS&KQ": "KQ"}, {"code": "194370", "KS&KQ": "KS"}, {"code": "170790", "KS&KQ": "KQ"}, {"code": "011420", "KS&KQ": "KS"}, {"code": "060540", "KS&KQ": "KQ"}, {"code": "009290", "KS&KQ": "KS"}, {"code": "028260", "KS&KQ": "KS"}, {"code": "043370", "KS&KQ": "KQ"}, {"code": "054630", "KS&KQ": "KQ"}, {"code": "024880", "KS&KQ": "KQ"}, {"code": "189690", "KS&KQ": "KQ"}, {"code": "003230", "KS&KQ": "KS"}, {"code": "099440", "KS&KQ": "KQ"}, {"code": "166480", "KS&KQ": "KQ"}, {"code": "006360", "KS&KQ": "KS"}, {"code": "077360", "KS&KQ": "KQ"}, {"code": "006200", "KS&KQ": "KS"}, {"code": "028300", "KS&KQ": "KQ"}, {"code": "058630", "KS&KQ": "KQ"}, {"code": "011230", "KS&KQ": "KS"}, {"code": "003620", "KS&KQ": "KS"}, {"code": "143210", "KS&KQ": "KS"}, {"code": "166090", "KS&KQ": "KQ"}, {"code": "089530", "KS&KQ": "KQ"}, {"code": "000300", "KS&KQ": "KS"}, {"code": "263810", "KS&KQ": "KQ"}, {"code": "083790", "KS&KQ": "KQ"}, {"code": "172580", "KS&KQ": "KS"}, {"code": "000880", "KS&KQ": "KS"}, {"code": "247540", "KS&KQ": "KQ"}, {"code": "250000", "KS&KQ": "KQ"}, {"code": "001340", "KS&KQ": "KS"}, {"code": "200780", "KS&KQ": "KQ"}, {"code": "008370", "KS&KQ": "KQ"}, {"code": "034310", "KS&KQ": "KS"}, {"code": "126700", "KS&KQ": "KQ"}, {"code": "030610", "KS&KQ": "KS"}, {"code": "003580", "KS&KQ": "KS"}, {"code": "083380", "KS&KQ": "KS"}, {"code": "092070", "KS&KQ": "KQ"}, {"code": "001630", "KS&KQ": "KS"}, {"code": "095910", "KS&KQ": "KQ"}, {"code": "054180", "KS&KQ": "KQ"}, {"code": "006620", "KS&KQ": "KQ"}, {"code": "138080", "KS&KQ": "KQ"}, {"code": "075180", "KS&KQ": "KS"}, {"code": "237690", "KS&KQ": "KQ"}, {"code": "060980", "KS&KQ": "KS"}, {"code": "030190", "KS&KQ": "KQ"}, {"code": "003200", "KS&KQ": "KS"}, {"code": "021880", "KS&KQ": "KQ"}, {"code": "069620", "KS&KQ": "KS"}, {"code": "037760", "KS&KQ": "KQ"}, {"code": "272290", "KS&KQ": "KQ"}, {"code": "041190", "KS&KQ": "KQ"}, {"code": "111770", "KS&KQ": "KS"}, {"code": "071090", "KS&KQ": "KS"}, {"code": "049080", "KS&KQ": "KQ"}, {"code": "226400", "KS&KQ": "KQ"}, {"code": "043220", "KS&KQ": "KQ"}, {"code": "009300", "KS&KQ": "KQ"}, {"code": "034730", "KS&KQ": "KS"}, {"code": "001210", "KS&KQ": "KS"}, {"code": "005710", "KS&KQ": "KQ"}, {"code": "174880", "KS&KQ": "KQ"}, {"code": "039980", "KS&KQ": "KQ"}, {"code": "130740", "KS&KQ": "KQ"}, {"code": "048770", "KS&KQ": "KQ"}, {"code": "027360", "KS&KQ": "KQ"}, {"code": "094800", "KS&KQ": "KS"}, {"code": "123890", "KS&KQ": "KS"}, {"code": "140890", "KS&KQ": "KS"}, {"code": "092040", "KS&KQ": "KQ"}, {"code": "035200", "KS&KQ": "KQ"}, {"code": "086960", "KS&KQ": "KQ"}, {"code": "023460", "KS&KQ": "KQ"}, {"code": "025950", "KS&KQ": "KQ"}, {"code": "010280", "KS&KQ": "KQ"}, {"code": "035000", "KS&KQ": "KS"}, {"code": "201490", "KS&KQ": "KQ"}, {"code": "089890", "KS&KQ": "KQ"}, {"code": "101400", "KS&KQ": "KQ"}, {"code": "079430", "KS&KQ": "KS"}, {"code": "114810", "KS&KQ": "KQ"}, {"code": "063440", "KS&KQ": "KQ"}, {"code": "004430", "KS&KQ": "KS"}, {"code": "088350", "KS&KQ": "KS"}, {"code": "032800", "KS&KQ": "KQ"}, {"code": "119850", "KS&KQ": "KQ"}, {"code": "009470", "KS&KQ": "KS"}, {"code": "192650", "KS&KQ": "KS"}, {"code": "052460", "KS&KQ": "KQ"}, {"code": "217190", "KS&KQ": "KQ"}, {"code": "053030", "KS&KQ": "KQ"}, {"code": "115500", "KS&KQ": "KQ"}, {"code": "007110", "KS&KQ": "KS"}, {"code": "271980", "KS&KQ": "KS"}, {"code": "082640", "KS&KQ": "KS"}, {"code": "004380", "KS&KQ": "KS"}, {"code": "042510", "KS&KQ": "KQ"}, {"code": "091990", "KS&KQ": "KQ"}, {"code": "102120", "KS&KQ": "KQ"}, {"code": "000910", "KS&KQ": "KS"}, {"code": "028050", "KS&KQ": "KS"}, {"code": "016800", "KS&KQ": "KS"}, {"code": "010040", "KS&KQ": "KS"}, {"code": "002450", "KS&KQ": "KS"}, {"code": "263770", "KS&KQ": "KQ"}, {"code": "037400", "KS&KQ": "KQ"}, {"code": "004960", "KS&KQ": "KS"}, {"code": "192080", "KS&KQ": "KQ"}, {"code": "001820", "KS&KQ": "KS"}, {"code": "020150", "KS&KQ": "KS"}, {"code": "060560", "KS&KQ": "KQ"}, {"code": "010050", "KS&KQ": "KS"}, {"code": "027830", "KS&KQ": "KQ"}, {"code": "028040", "KS&KQ": "KQ"}, {"code": "005850", "KS&KQ": "KS"}, {"code": "024120", "KS&KQ": "KQ"}, {"code": "050110", "KS&KQ": "KQ"}, {"code": "000860", "KS&KQ": "KS"}, {"code": "069140", "KS&KQ": "KQ"}, {"code": "048830", "KS&KQ": "KQ"}, {"code": "005930", "KS&KQ": "KS"}, {"code": "036120", "KS&KQ": "KQ"}, {"code": "008970", "KS&KQ": "KS"}, {"code": "226360", "KS&KQ": "KQ"}, {"code": "079810", "KS&KQ": "KQ"}, {"code": "011560", "KS&KQ": "KQ"}, {"code": "047040", "KS&KQ": "KS"}, {"code": "009460", "KS&KQ": "KS"}, {"code": "004150", "KS&KQ": "KS"}, {"code": "005500", "KS&KQ": "KS"}, {"code": "054940", "KS&KQ": "KQ"}, {"code": "261200", "KS&KQ": "KQ"}, {"code": "039010", "KS&KQ": "KQ"}, {"code": "051390", "KS&KQ": "KQ"}, {"code": "009070", "KS&KQ": "KS"}, {"code": "012450", "KS&KQ": "KS"}, {"code": "069960", "KS&KQ": "KS"}, {"code": "005110", "KS&KQ": "KS"}, {"code": "008420", "KS&KQ": "KS"}, {"code": "013000", "KS&KQ": "KS"}, {"code": "041020", "KS&KQ": "KQ"}, {"code": "006380", "KS&KQ": "KS"}, {"code": "310200", "KS&KQ": "KQ"}, {"code": "031510", "KS&KQ": "KQ"}, {"code": "093370", "KS&KQ": "KS"}, {"code": "210980", "KS&KQ": "KS"}, {"code": "214270", "KS&KQ": "KQ"}, {"code": "009270", "KS&KQ": "KS"}, {"code": "277070", "KS&KQ": "KQ"}, {"code": "032580", "KS&KQ": "KQ"}, {"code": "089470", "KS&KQ": "KS"}, {"code": "140670", "KS&KQ": "KQ"}, {"code": "035760", "KS&KQ": "KQ"}, {"code": "138250", "KS&KQ": "KS"}, {"code": "028080", "KS&KQ": "KQ"}, {"code": "001200", "KS&KQ": "KS"}, {"code": "036490", "KS&KQ": "KQ"}, {"code": "032190", "KS&KQ": "KQ"}, {"code": "136490", "KS&KQ": "KS"}, {"code": "055490", "KS&KQ": "KS"}, {"code": "271560", "KS&KQ": "KS"}, {"code": "203690", "KS&KQ": "KQ"}, {"code": "015710", "KS&KQ": "KQ"}, {"code": "011210", "KS&KQ": "KS"}, {"code": "016580", "KS&KQ": "KS"}, {"code": "072990", "KS&KQ": "KQ"}, {"code": "002720", "KS&KQ": "KS"}, {"code": "155650", "KS&KQ": "KQ"}, {"code": "160600", "KS&KQ": "KQ"}, {"code": "073640", "KS&KQ": "KQ"}, {"code": "212560", "KS&KQ": "KQ"}, {"code": "006340", "KS&KQ": "KS"}, {"code": "050890", "KS&KQ": "KQ"}, {"code": "088790", "KS&KQ": "KS"}, {"code": "041590", "KS&KQ": "KQ"}, {"code": "047810", "KS&KQ": "KS"}, {"code": "010960", "KS&KQ": "KS"}, {"code": "042940", "KS&KQ": "KQ"}, {"code": "104040", "KS&KQ": "KQ"}, {"code": "133820", "KS&KQ": "KS"}, {"code": "145020", "KS&KQ": "KQ"}, {"code": "181710", "KS&KQ": "KS"}, {"code": "066410", "KS&KQ": "KQ"}, {"code": "002790", "KS&KQ": "KS"}, {"code": "123010", "KS&KQ": "KQ"}, {"code": "131400", "KS&KQ": "KQ"}, {"code": "096640", "KS&KQ": "KQ"}, {"code": "009160", "KS&KQ": "KS"}, {"code": "049550", "KS&KQ": "KQ"}, {"code": "004450", "KS&KQ": "KS"}, {"code": "237750", "KS&KQ": "KQ"}, {"code": "197210", "KS&KQ": "KQ"}, {"code": "151860", "KS&KQ": "KQ"}, {"code": "058850", "KS&KQ": "KS"}, {"code": "030520", "KS&KQ": "KQ"}, {"code": "018290", "KS&KQ": "KQ"}, {"code": "119830", "KS&KQ": "KQ"}, {"code": "144510", "KS&KQ": "KQ"}, {"code": "052400", "KS&KQ": "KQ"}, {"code": "012030", "KS&KQ": "KS"}, {"code": "036810", "KS&KQ": "KQ"}, {"code": "041440", "KS&KQ": "KQ"}, {"code": "053050", "KS&KQ": "KQ"}, {"code": "095610", "KS&KQ": "KQ"}, {"code": "299910", "KS&KQ": "KQ"}, {"code": "014440", "KS&KQ": "KS"}, {"code": "006050", "KS&KQ": "KQ"}, {"code": "003470", "KS&KQ": "KS"}, {"code": "000810", "KS&KQ": "KS"}, {"code": "053290", "KS&KQ": "KQ"}, {"code": "037070", "KS&KQ": "KQ"}, {"code": "200880", "KS&KQ": "KS"}, {"code": "217330", "KS&KQ": "KQ"}, {"code": "083310", "KS&KQ": "KQ"}, {"code": "026960", "KS&KQ": "KS"}, {"code": "039840", "KS&KQ": "KQ"}, {"code": "067900", "KS&KQ": "KQ"}, {"code": "065130", "KS&KQ": "KQ"}, {"code": "204210", "KS&KQ": "KS"}, {"code": "136540", "KS&KQ": "KQ"}, {"code": "029460", "KS&KQ": "KS"}, {"code": "036540", "KS&KQ": "KQ"}, {"code": "313750", "KS&KQ": "KQ"}, {"code": "067280", "KS&KQ": "KQ"}, {"code": "019010", "KS&KQ": "KQ"}, {"code": "110020", "KS&KQ": "KQ"}, {"code": "042000", "KS&KQ": "KQ"}, {"code": "222980", "KS&KQ": "KQ"}, {"code": "037460", "KS&KQ": "KQ"}, {"code": "084680", "KS&KQ": "KS"}, {"code": "088910", "KS&KQ": "KQ"}, {"code": "084870", "KS&KQ": "KS"}, {"code": "090150", "KS&KQ": "KQ"}, {"code": "307280", "KS&KQ": "KQ"}, {"code": "258790", "KS&KQ": "KQ"}, {"code": "086040", "KS&KQ": "KQ"}, {"code": "007210", "KS&KQ": "KS"}, {"code": "099410", "KS&KQ": "KQ"}, {"code": "096870", "KS&KQ": "KQ"}, {"code": "033200", "KS&KQ": "KQ"}, {"code": "026180", "KS&KQ": "KQ"}, {"code": "158310", "KS&KQ": "KQ"}, {"code": "046890", "KS&KQ": "KQ"}, {"code": "097950", "KS&KQ": "KS"}, {"code": "069330", "KS&KQ": "KQ"}, {"code": "072710", "KS&KQ": "KS"}, {"code": "025890", "KS&KQ": "KS"}, {"code": "037270", "KS&KQ": "KS"}, {"code": "046310", "KS&KQ": "KQ"}, {"code": "007370", "KS&KQ": "KQ"}, {"code": "088130", "KS&KQ": "KQ"}, {"code": "293580", "KS&KQ": "KQ"}, {"code": "006090", "KS&KQ": "KS"}, {"code": "241820", "KS&KQ": "KQ"}, {"code": "052600", "KS&KQ": "KQ"}, {"code": "225430", "KS&KQ": "KQ"}, {"code": "089010", "KS&KQ": "KQ"}, {"code": "131370", "KS&KQ": "KQ"}, {"code": "023760", "KS&KQ": "KQ"}, {"code": "051490", "KS&KQ": "KQ"}, {"code": "034220", "KS&KQ": "KS"}, {"code": "108320", "KS&KQ": "KQ"}, {"code": "009770", "KS&KQ": "KS"}, {"code": "036580", "KS&KQ": "KS"}, {"code": "049630", "KS&KQ": "KQ"}, {"code": "086900", "KS&KQ": "KQ"}, {"code": "131760", "KS&KQ": "KQ"}, {"code": "242040", "KS&KQ": "KQ"}, {"code": "291230", "KS&KQ": "KQ"}, {"code": "101670", "KS&KQ": "KQ"}, {"code": "004720", "KS&KQ": "KS"}, {"code": "080420", "KS&KQ": "KQ"}, {"code": "001880", "KS&KQ": "KS"}, {"code": "100220", "KS&KQ": "KS"}, {"code": "012630", "KS&KQ": "KS"}, {"code": "206400", "KS&KQ": "KQ"}, {"code": "224110", "KS&KQ": "KQ"}, {"code": "096040", "KS&KQ": "KQ"}, {"code": "273060", "KS&KQ": "KQ"}, {"code": "004250", "KS&KQ": "KS"}, {"code": "017370", "KS&KQ": "KS"}, {"code": "041650", "KS&KQ": "KS"}, {"code": "161580", "KS&KQ": "KQ"}, {"code": "005990", "KS&KQ": "KQ"}, {"code": "038620", "KS&KQ": "KQ"}, {"code": "900270", "KS&KQ": "KQ"}, {"code": "036180", "KS&KQ": "KQ"}, {"code": "010620", "KS&KQ": "KS"}, {"code": "042370", "KS&KQ": "KQ"}, {"code": "003310", "KS&KQ": "KQ"}, {"code": "279410", "KS&KQ": "KQ"}, {"code": "000180", "KS&KQ": "KS"}, {"code": "032640", "KS&KQ": "KS"}, {"code": "037710", "KS&KQ": "KS"}, {"code": "054670", "KS&KQ": "KQ"}, {"code": "000590", "KS&KQ": "KS"}, {"code": "004090", "KS&KQ": "KS"}, {"code": "092780", "KS&KQ": "KS"}, {"code": "033600", "KS&KQ": "KQ"}, {"code": "004910", "KS&KQ": "KS"}, {"code": "008870", "KS&KQ": "KS"}, {"code": "001840", "KS&KQ": "KQ"}, {"code": "217730", "KS&KQ": "KQ"}, {"code": "067290", "KS&KQ": "KQ"}, {"code": "239340", "KS&KQ": "KQ"}, {"code": "122900", "KS&KQ": "KS"}, {"code": "003070", "KS&KQ": "KS"}, {"code": "055550", "KS&KQ": "KS"}, {"code": "007570", "KS&KQ": "KS"}, {"code": "002420", "KS&KQ": "KS"}, {"code": "005830", "KS&KQ": "KS"}, {"code": "100790", "KS&KQ": "KQ"}, {"code": "267980", "KS&KQ": "KQ"}, {"code": "183300", "KS&KQ": "KQ"}, {"code": "019570", "KS&KQ": "KQ"}, {"code": "002150", "KS&KQ": "KS"}, {"code": "033560", "KS&KQ": "KQ"}, {"code": "005950", "KS&KQ": "KS"}, {"code": "115570", "KS&KQ": "KQ"}, {"code": "038390", "KS&KQ": "KQ"}, {"code": "065530", "KS&KQ": "KQ"}, {"code": "080580", "KS&KQ": "KQ"}, {"code": "012790", "KS&KQ": "KQ"}, {"code": "084730", "KS&KQ": "KQ"}, {"code": "001060", "KS&KQ": "KS"}, {"code": "057540", "KS&KQ": "KQ"}, {"code": "081660", "KS&KQ": "KS"}, {"code": "030530", "KS&KQ": "KQ"}, {"code": "043290", "KS&KQ": "KQ"}, {"code": "005010", "KS&KQ": "KS"}, {"code": "057030", "KS&KQ": "KQ"}, {"code": "001510", "KS&KQ": "KS"}, {"code": "089980", "KS&KQ": "KQ"}, {"code": "007820", "KS&KQ": "KQ"}, {"code": "026150", "KS&KQ": "KQ"}, {"code": "023000", "KS&KQ": "KS"}, {"code": "092230", "KS&KQ": "KS"}, {"code": "038540", "KS&KQ": "KQ"}, {"code": "084650", "KS&KQ": "KQ"}, {"code": "051910", "KS&KQ": "KS"}, {"code": "194480", "KS&KQ": "KQ"}, {"code": "014280", "KS&KQ": "KS"}, {"code": "010780", "KS&KQ": "KS"}, {"code": "151910", "KS&KQ": "KQ"}]